{
    "total": [
        {
            "id": "100084868117065",
            "count": 10
        },
        {
            "id": "100030967444445",
            "count": 3
        },
        {
            "id": "100087652159146",
            "count": 1
        }
    ],
    "week": [
        {
            "id": "100084868117065",
            "count": 0,
            "name": "Lê Bá Bách"
        },
        {
            "id": "100030967444445",
            "count": 1,
            "name": "Duy Khánh"
        },
        {
            "id": "100087652159146",
            "count": 1
        }
    ],
    "day": [
        {
            "id": "100084868117065",
            "count": 0,
            "name": "Lê Bá Bách"
        },
        {
            "id": "100030967444445",
            "count": 0,
            "name": "Duy Khánh"
        },
        {
            "id": "100087652159146",
            "count": 0,
            "name": "Lê Bá Bách"
        }
    ],
    "time": 4
}